Yusir
img
