Metadata-Version: 2.1
Name: Yusir
Version: 0.1.12
Summary: some Common functions 
Author: clever Yusir
Author-email: linxing_1@163.com
